sptemp/__init__.py
sptemp/_texts.py
sptemp/analysis.py
sptemp/interpolation.py
sptemp/moving_geometry.py
sptemp/zeit.py
sptemp/tests/__init__.py
sptemp/tests/analysis_tests.py
sptemp/tests/interpolation_tests.py
sptemp/tests/moving_geometry_tests.py
sptemp/tests/zeit_tests.py
sptemp-1.1.0.dist-info/LICENSE.txt
sptemp-1.1.0.dist-info/METADATA
sptemp-1.1.0.dist-info/WHEEL
sptemp-1.1.0.dist-info/top_level.txt
sptemp-1.1.0.dist-info/RECORD
