Metadata-Version: 2.1
Name: sptemp
Version: 1.1.0
Summary: package for spatio-temporal vector data processing and analysis.
Home-page: https://github.com/BaumannDaniel/sptemp
Author: Daniel Baumann
Author-email: baumann-dan@outlook.com
License: UNKNOWN
Platform: UNKNOWN
Classifier: Programming Language :: Python :: 2
Classifier: Programming Language :: Python :: 2.7
Classifier: License :: OSI Approved :: MIT License
Classifier: Operating System :: OS Independent
